dtaianomaly/__init__.py
dtaianomaly/anomaly_detection/_AutoEncoder.py
dtaianomaly/anomaly_detection/_BaseDetector.py
dtaianomaly/anomaly_detection/_BaseNeuralDetector.py
dtaianomaly/anomaly_detection/_BaseNeuralForecastingDetector.py
dtaianomaly/anomaly_detection/_BaseNeuralReconstructionDetector.py
dtaianomaly/anomaly_detection/_BasePyODAnomalyDetector.py
dtaianomaly/anomaly_detection/_Chronos.py
dtaianomaly/anomaly_detection/_ClusterBasedLocalOutlierFactor.py
dtaianomaly/anomaly_detection/_ConvolutionalNeuralNetwork.py
dtaianomaly/anomaly_detection/_CopulaBasedOutlierDetector.py
dtaianomaly/anomaly_detection/_DWT_MLEAD.py
dtaianomaly/anomaly_detection/_HistogramBasedOutlierScore.py
dtaianomaly/anomaly_detection/_HybridKNearestNeighbors.py
dtaianomaly/anomaly_detection/_IsolationForest.py
dtaianomaly/anomaly_detection/_KMeansAnomalyDetector.py
dtaianomaly/anomaly_detection/_KNearestNeighbors.py
dtaianomaly/anomaly_detection/_KShapeAnomalyDetector.py
dtaianomaly/anomaly_detection/_KernelPrincipalComponentAnalysis.py
dtaianomaly/anomaly_detection/_LocalOutlierFactor.py
dtaianomaly/anomaly_detection/_LocalPolynomialApproximation.py
dtaianomaly/anomaly_detection/_LongShortTermMemoryNetwork.py
dtaianomaly/anomaly_detection/_MOMENT.py
dtaianomaly/anomaly_detection/_MatrixProfileDetector.py
dtaianomaly/anomaly_detection/_MedianMethod.py
dtaianomaly/anomaly_detection/_MultilayerPerceptron.py
dtaianomaly/anomaly_detection/_MultivariateDetector.py
dtaianomaly/anomaly_detection/_OneClassSupportVectorMachine.py
dtaianomaly/anomaly_detection/_PrincipalComponentAnalysis.py
dtaianomaly/anomaly_detection/_ROCKAD.py
dtaianomaly/anomaly_detection/_RobustPrincipalComponentAnalysis.py
dtaianomaly/anomaly_detection/_RobustRandomCutForestAnomalyDetector.py
dtaianomaly/anomaly_detection/_SpectralResidual.py
dtaianomaly/anomaly_detection/_TimeMoE.py
dtaianomaly/anomaly_detection/_TorchTimeSeriesDataSet.py
dtaianomaly/anomaly_detection/_Transformer.py
dtaianomaly-0.5.1.dist-info/licenses/LICENSE
dtaianomaly-0.5.1.dist-info/METADATA
dtaianomaly-0.5.1.dist-info/WHEEL
dtaianomaly-0.5.1.dist-info/top_level.txt
dtaianomaly-0.5.1.dist-info/RECORD
