Metadata-Version: 2.4
Name: dtaianomaly
Version: 0.5.1
Summary: A simple-to-use Python package for time series anomaly detection!
Author-email: Louis Carpentier <louis.carpentier@kuleuven.be>
License: MIT License
Project-URL: homepage, https://pypi.org/project/dtaianomaly/
Project-URL: repository, https://github.com/ML-KULeuven/dtaianomaly
Project-URL: changelog, https://github.com/ML-KULeuven/dtaianomaly/blob/main/CHANGELOG.md
Project-URL: documentation, https://dtaianomaly.readthedocs.io/en/stable/index.html
Keywords: machine-learning,time-series,anomaly-detection,data-mining
Classifier: Development Status :: 4 - Beta
Classifier: License :: OSI Approved :: MIT License
Classifier: Programming Language :: Python :: 3.10
Classifier: Programming Language :: Python :: 3.11
Classifier: Programming Language :: Python :: 3.12
Classifier: Programming Language :: Python :: 3.13
Requires-Python: <3.14,>=3.10
License-File: LICENSE
Requires-Dist: numpy>=1.22
Requires-Dist: scipy>=1.10
Requires-Dist: numba>=0.58
Requires-Dist: stumpy>=1.12
Requires-Dist: scikit-learn>=1.3
Requires-Dist: pandas>=1.3.0
Requires-Dist: matplotlib>=3.7
Requires-Dist: statsmodels>=0.6
Requires-Dist: pyod>=2.0.0
Requires-Dist: tslearn>=0.6.3
Requires-Dist: sktime
Requires-Dist: toml
Requires-Dist: torch>=1.8.0
Provides-Extra: all
Requires-Dist: sphinx; extra == "all"
Requires-Dist: sphinx-rtd-theme; extra == "all"
Requires-Dist: numpydoc; extra == "all"
Requires-Dist: toml; extra == "all"
Requires-Dist: pytest; extra == "all"
Requires-Dist: pytest-cov; extra == "all"
Requires-Dist: notebook; extra == "all"
Requires-Dist: jupyterlab; extra == "all"
Requires-Dist: pre-commit; extra == "all"
Requires-Dist: black; extra == "all"
Requires-Dist: isort; extra == "all"
Requires-Dist: tqdm; extra == "all"
Requires-Dist: sphinxcontrib-bibtex; extra == "all"
Requires-Dist: tqdm; extra == "all"
Provides-Extra: tests
Requires-Dist: pytest; extra == "tests"
Requires-Dist: pytest-cov; extra == "tests"
Provides-Extra: tqdm
Requires-Dist: tqdm; extra == "tqdm"
Provides-Extra: docs
Requires-Dist: sphinx; extra == "docs"
Requires-Dist: sphinx-rtd-theme; extra == "docs"
Requires-Dist: numpydoc; extra == "docs"
Requires-Dist: sphinxcontrib-bibtex; extra == "docs"
Provides-Extra: notebooks
Requires-Dist: notebook; extra == "notebooks"
Requires-Dist: jupyterlab; extra == "notebooks"
Provides-Extra: lint
Requires-Dist: pre-commit; extra == "lint"
Requires-Dist: black; extra == "lint"
Requires-Dist: isort; extra == "lint"
Provides-Extra: chronos
Requires-Dist: autogluon.timeseries>=1.3.1; extra == "chronos"
Provides-Extra: moment
Requires-Dist: momentfm; extra == "moment"
Provides-Extra: time-moe
Requires-Dist: transformers==4.40.1; extra == "time-moe"
Dynamic: license-file
